rdaei/__init__.py
rdaei/analyze.py
rdaei/minority.py
rdaei-0.3.0.dist-info/LICENSE
rdaei-0.3.0.dist-info/METADATA
rdaei-0.3.0.dist-info/WHEEL
rdaei-0.3.0.dist-info/top_level.txt
rdaei-0.3.0.dist-info/RECORD
