Metadata-Version: 2.1
Name: rdaei
Version: 0.3.0
Summary: Redistricting ensembles
Home-page: https://github.com/rdatools/rdaei
Author: alecramsay
Author-email: Alec Ramsay <a73cram5ay@gmail.com>
License: MIT
Project-URL: Homepage, https://github.com/rdatools/rdaei
Project-URL: Bug Tracker, https://github.com/rdatools/rdabase/issues
Classifier: Programming Language :: Python :: 3
Classifier: License :: OSI Approved :: MIT License
Classifier: Operating System :: OS Independent
Requires-Python: >=3.10
License-File: LICENSE
Requires-Dist: rdabase
